.coveragerc
.travis.yml
LICENSE
MANIFEST.in
README.rst
setup.cfg
setup.py
Mopidy_OE1.egg-info/PKG-INFO
Mopidy_OE1.egg-info/SOURCES.txt
Mopidy_OE1.egg-info/dependency_links.txt
Mopidy_OE1.egg-info/entry_points.txt
Mopidy_OE1.egg-info/not-zip-safe
Mopidy_OE1.egg-info/requires.txt
Mopidy_OE1.egg-info/top_level.txt
mopidy_oe1/__init__.py
mopidy_oe1/backend.py
mopidy_oe1/client.py
mopidy_oe1/ext.conf
mopidy_oe1/library.py
mopidy_oe1/playback.py
tests/__init__.py
tests/test_client.py
tests/test_extension.py
tests/test_library.py
tests/test_playback.py
tests/utils.py