Metadata-Version: 1.1
Name: Mopidy-OE1
Version: 0.1.0
Summary: Mopidy backend to access the Austrian radio station OE1.
Home-page: https://github.com/tischlda/mopidy-oe1
Author: David Tischler
Author-email: david@tischler.io
License: Apache License, Version 2.0
Platform: UNKNOWN
Classifier: Environment :: No Input/Output (Daemon)
Classifier: Intended Audience :: End Users/Desktop
Classifier: License :: OSI Approved :: Apache Software License
Classifier: Operating System :: OS Independent
Classifier: Programming Language :: Python :: 2
Classifier: Topic :: Multimedia :: Sound/Audio :: Players
